mopidy_hearthis/__init__.py
mopidy_hearthis/backend.py
mopidy_hearthis/ext.conf
mopidy_hearthis/hearthis_search.py
mopidy_hearthis/library.py
Mopidy_Hearthis-0.2.3.dist-info/LICENSE
Mopidy_Hearthis-0.2.3.dist-info/METADATA
Mopidy_Hearthis-0.2.3.dist-info/WHEEL
Mopidy_Hearthis-0.2.3.dist-info/entry_points.txt
Mopidy_Hearthis-0.2.3.dist-info/top_level.txt
Mopidy_Hearthis-0.2.3.dist-info/RECORD
